aliyun_sdk_secretsmanager_oss_plugin/__init__.py
aliyun_sdk_secretsmanager_oss_plugin/oss_ak_expire_handler.py
aliyun_sdk_secretsmanager_oss_plugin/proxy_bucket.py
aliyun_sdk_secretsmanager_oss_plugin/secretsmanager_oss_plugin_credential_updater.py
aliyun_sdk_secretsmanager_oss_plugin/secretsmanager_oss_plugin_manager.py
aliyun_sdk_secretsmanager_oss_plugin/secretsmanger_plugin_auth.py
jepson_aliyun_oss_python_sdk_managed_credentials_provider-0.1.5.dist-info/METADATA
jepson_aliyun_oss_python_sdk_managed_credentials_provider-0.1.5.dist-info/WHEEL
jepson_aliyun_oss_python_sdk_managed_credentials_provider-0.1.5.dist-info/top_level.txt
jepson_aliyun_oss_python_sdk_managed_credentials_provider-0.1.5.dist-info/RECORD
